<?xml version="1.0" encoding="UTF-8"?><record_update>
    <sys_choice action="INSERT_OR_UPDATE" field="u_origin_movement" table="x_606284_stock_mov_x_606284_movstock" version="3">
        <sys_choice_set action="INSERT_OR_UPDATE">
            <element>u_origin_movement</element>
            <name>x_606284_stock_mov_x_606284_movstock</name>
            <sys_class_name>sys_choice_set</sys_class_name>
            <sys_created_by>BL62F3EN</sys_created_by>
            <sys_created_on>2025-06-27 15:36:31</sys_created_on>
            <sys_mod_count>0</sys_mod_count>
            <sys_name>u_origin_movement</sys_name>
            <sys_package display_value="stock movement" source="x_606284_stock_mov">378f720b835a6a9048d6ccc6feaad37c</sys_package>
            <sys_policy/>
            <sys_scope display_value="stock movement">378f720b835a6a9048d6ccc6feaad37c</sys_scope>
            <sys_update_name>sys_choice_x_606284_stock_mov_x_606284_movstock_u_origin_movement</sys_update_name>
            <sys_updated_by>BL62F3EN</sys_updated_by>
            <sys_updated_on>2025-06-27 15:36:31</sys_updated_on>
        </sys_choice_set>
        <sys_choice action="INSERT_OR_UPDATE">
            <dependent_value/>
            <element>u_origin_movement</element>
            <hint/>
            <inactive>false</inactive>
            <label>Supplier reception</label>
            <language>en</language>
            <name>x_606284_stock_mov_x_606284_movstock</name>
            <sequence>10</sequence>
            <synonyms/>
            <sys_created_by>BL62F3EN</sys_created_by>
            <sys_created_on>2025-06-27 15:36:31</sys_created_on>
            <sys_domain>global</sys_domain>
            <sys_domain_path>/</sys_domain_path>
            <sys_mod_count>3</sys_mod_count>
            <sys_updated_by>BL62F3EN</sys_updated_by>
            <sys_updated_on>2025-06-27 15:39:40</sys_updated_on>
            <value>u_supplier_reception</value>
        </sys_choice>
        <sys_choice action="INSERT_OR_UPDATE">
            <dependent_value/>
            <element>u_origin_movement</element>
            <hint/>
            <inactive>false</inactive>
            <label>Stock transfer</label>
            <language>en</language>
            <name>x_606284_stock_mov_x_606284_movstock</name>
            <sequence>20</sequence>
            <synonyms/>
            <sys_created_by>BL62F3EN</sys_created_by>
            <sys_created_on>2025-06-27 15:39:07</sys_created_on>
            <sys_domain>global</sys_domain>
            <sys_domain_path>/</sys_domain_path>
            <sys_mod_count>2</sys_mod_count>
            <sys_updated_by>BL62F3EN</sys_updated_by>
            <sys_updated_on>2025-06-27 15:39:27</sys_updated_on>
            <value>u_stock_transfer</value>
        </sys_choice>
        <sys_choice action="INSERT_OR_UPDATE">
            <dependent_value/>
            <element>u_origin_movement</element>
            <hint/>
            <inactive>false</inactive>
            <label>Lost</label>
            <language>en</language>
            <name>x_606284_stock_mov_x_606284_movstock</name>
            <sequence>30</sequence>
            <synonyms/>
            <sys_created_by>BL62F3EN</sys_created_by>
            <sys_created_on>2025-06-27 15:44:54</sys_created_on>
            <sys_domain>global</sys_domain>
            <sys_domain_path>/</sys_domain_path>
            <sys_mod_count>4</sys_mod_count>
            <sys_updated_by>BL62F3EN</sys_updated_by>
            <sys_updated_on>2025-11-26 09:08:06</sys_updated_on>
            <value>u_lost</value>
        </sys_choice>
        <sys_choice action="INSERT_OR_UPDATE">
            <dependent_value/>
            <element>u_origin_movement</element>
            <hint/>
            <inactive>false</inactive>
            <label>Supplier return</label>
            <language>en</language>
            <name>x_606284_stock_mov_x_606284_movstock</name>
            <sequence>40</sequence>
            <synonyms/>
            <sys_created_by>BL62F3EN</sys_created_by>
            <sys_created_on>2025-06-27 15:46:12</sys_created_on>
            <sys_domain>global</sys_domain>
            <sys_domain_path>/</sys_domain_path>
            <sys_mod_count>2</sys_mod_count>
            <sys_updated_by>BL62F3EN</sys_updated_by>
            <sys_updated_on>2025-06-27 15:46:35</sys_updated_on>
            <value>u_supplier_return</value>
        </sys_choice>
        <sys_choice action="INSERT_OR_UPDATE">
            <dependent_value/>
            <element>u_origin_movement</element>
            <hint/>
            <inactive>false</inactive>
            <label>Installation</label>
            <language>en</language>
            <name>x_606284_stock_mov_x_606284_movstock</name>
            <sequence>50</sequence>
            <synonyms/>
            <sys_created_by>BL62F3EN</sys_created_by>
            <sys_created_on>2025-06-27 15:47:54</sys_created_on>
            <sys_domain>global</sys_domain>
            <sys_domain_path>/</sys_domain_path>
            <sys_mod_count>2</sys_mod_count>
            <sys_updated_by>BL62F3EN</sys_updated_by>
            <sys_updated_on>2025-06-27 15:48:08</sys_updated_on>
            <value>u_installation</value>
        </sys_choice>
        <sys_choice action="INSERT_OR_UPDATE">
            <dependent_value/>
            <element>u_origin_movement</element>
            <hint/>
            <inactive>false</inactive>
            <label>Stolen</label>
            <language>en</language>
            <name>x_606284_stock_mov_x_606284_movstock</name>
            <sequence>60</sequence>
            <synonyms/>
            <sys_created_by>BL62F3EN</sys_created_by>
            <sys_created_on>2025-06-27 15:48:47</sys_created_on>
            <sys_domain>global</sys_domain>
            <sys_domain_path>/</sys_domain_path>
            <sys_mod_count>2</sys_mod_count>
            <sys_updated_by>BL62F3EN</sys_updated_by>
            <sys_updated_on>2025-06-27 15:49:01</sys_updated_on>
            <value>u_stolen</value>
        </sys_choice>
        <sys_choice action="INSERT_OR_UPDATE">
            <dependent_value/>
            <element>u_origin_movement</element>
            <hint/>
            <inactive>false</inactive>
            <label>Reprise</label>
            <language>en</language>
            <name>x_606284_stock_mov_x_606284_movstock</name>
            <sequence>70</sequence>
            <synonyms/>
            <sys_created_by>BL62F3EN</sys_created_by>
            <sys_created_on>2025-06-27 15:50:57</sys_created_on>
            <sys_domain>global</sys_domain>
            <sys_domain_path>/</sys_domain_path>
            <sys_mod_count>2</sys_mod_count>
            <sys_updated_by>BL62F3EN</sys_updated_by>
            <sys_updated_on>2025-06-27 15:51:11</sys_updated_on>
            <value>u_reprise</value>
        </sys_choice>
        <sys_choice action="INSERT_OR_UPDATE">
            <dependent_value/>
            <element>u_origin_movement</element>
            <hint/>
            <inactive>false</inactive>
            <label>RMA</label>
            <language>en</language>
            <name>x_606284_stock_mov_x_606284_movstock</name>
            <sequence>80</sequence>
            <synonyms/>
            <sys_created_by>BL62F3EN</sys_created_by>
            <sys_created_on>2025-11-26 08:18:18</sys_created_on>
            <sys_domain>global</sys_domain>
            <sys_domain_path>/</sys_domain_path>
            <sys_mod_count>1</sys_mod_count>
            <sys_updated_by>BL62F3EN</sys_updated_by>
            <sys_updated_on>2025-11-26 08:19:09</sys_updated_on>
            <value>u_rma</value>
        </sys_choice>
        <sys_choice action="INSERT_OR_UPDATE">
            <dependent_value/>
            <element>u_origin_movement</element>
            <hint/>
            <inactive>false</inactive>
            <label>Inventory</label>
            <language>en</language>
            <name>x_606284_stock_mov_x_606284_movstock</name>
            <sequence>85</sequence>
            <synonyms/>
            <sys_created_by>BL62F3EN</sys_created_by>
            <sys_created_on>2025-11-26 09:40:50</sys_created_on>
            <sys_domain>global</sys_domain>
            <sys_domain_path>/</sys_domain_path>
            <sys_mod_count>2</sys_mod_count>
            <sys_updated_by>BL62F3EN</sys_updated_by>
            <sys_updated_on>2025-11-26 09:41:15</sys_updated_on>
            <value>u_inventory</value>
        </sys_choice>
        <sys_choice action="INSERT_OR_UPDATE">
            <dependent_value/>
            <element>u_origin_movement</element>
            <hint/>
            <inactive>false</inactive>
            <label>Other</label>
            <language>en</language>
            <name>x_606284_stock_mov_x_606284_movstock</name>
            <sequence>90</sequence>
            <synonyms/>
            <sys_created_by>BL62F3EN</sys_created_by>
            <sys_created_on>2025-11-26 08:38:25</sys_created_on>
            <sys_domain>global</sys_domain>
            <sys_domain_path>/</sys_domain_path>
            <sys_mod_count>2</sys_mod_count>
            <sys_updated_by>BL62F3EN</sys_updated_by>
            <sys_updated_on>2025-11-26 08:38:52</sys_updated_on>
            <value>u_other</value>
        </sys_choice>
    </sys_choice>
</record_update>
